<?xml version="1.0" encoding="utf-8" ?><dwsync><file name=".htaccess" server="cine-track.xsrv.jp" local="3518638939" remote="3517440900" Dst="-1" /><file name="license.txt" server="cine-track.xsrv.jp" local="3518638939" remote="3502882800" Dst="-1" /><file name="index.php" server="cine-track.xsrv.jp" local="3518638939" remote="3462879600" Dst="-1" /><file name="readme.html" server="cine-track.xsrv.jp" local="3518638939" remote="3512799840" Dst="-1" /><file name="wp-activate.php" server="cine-track.xsrv.jp" local="3518638939" remote="3491391600" Dst="-1" /><file name="wp-blog-header.php" server="cine-track.xsrv.jp" local="3518638983" remote="3408879600" Dst="-1" /><file name="wp-comments-post.php" server="cine-track.xsrv.jp" local="3518638983" remote="3503545500" Dst="-1" /><file name="wp-config.php" server="cine-track.xsrv.jp" local="3518638983" remote="3517440900" Dst="-1" /><file name="wp-config-sample.php" server="cine-track.xsrv.jp" local="3518638983" remote="3512799840" Dst="-1" /><file name="wp-cron.php" server="cine-track.xsrv.jp" local="3518639213" remote="3509480280" Dst="-1" /><file name="wp-links-opml.php" server="cine-track.xsrv.jp" local="3518639279" remote="3465471600" Dst="-1" /><file name="wp-load.php" server="cine-track.xsrv.jp" local="3518639280" remote="3511718940" Dst="-1" /><file name="wp-login.php" server="cine-track.xsrv.jp" local="3518639280" remote="3511718940" Dst="-1" /><file name="wp-mail.php" server="cine-track.xsrv.jp" local="3518639280" remote="3488367600" Dst="-1" /><file name="wp-settings.php" server="cine-track.xsrv.jp" local="3518639280" remote="3511718940" Dst="-1" /><file name="wp-trackback.php" server="cine-track.xsrv.jp" local="3518639280" remote="3500204400" Dst="-1" /><file name="wp-signup.php" server="cine-track.xsrv.jp" local="3518639280" remote="3500204400" Dst="-1" /><file name="xmlrpc.php" server="cine-track.xsrv.jp" local="3518639280" remote="3474802800" Dst="-1" /></dwsync>